MANIFEST.in
README.rst
setup.py
django_mootools_behavior.egg-info/PKG-INFO
django_mootools_behavior.egg-info/SOURCES.txt
django_mootools_behavior.egg-info/dependency_links.txt
django_mootools_behavior.egg-info/not-zip-safe
django_mootools_behavior.egg-info/requires.txt
django_mootools_behavior.egg-info/top_level.txt
mootools_behavior/__init__.py
mootools_behavior/assets.py
mootools_behavior/models.py
mootools_behavior/static/mootools_behavior/Behavior/Behavior.js
mootools_behavior/static/mootools_behavior/Behavior/BehaviorAPI.js
mootools_behavior/static/mootools_behavior/Behavior/Delegator.js
mootools_behavior/static/mootools_behavior/Behavior/Element.Data.js
mootools_behavior/static/mootools_behavior/Behavior/Event.Mock.js
mootools_behavior/static/mootools_behavior/Behavior.More/Delegators/Delegator.AddRemoveClass.js
mootools_behavior/static/mootools_behavior/Behavior.More/Delegators/Delegator.Ajax.js
mootools_behavior/static/mootools_behavior/Behavior.More/Delegators/Delegator.CheckAllOrNone.js
mootools_behavior/static/mootools_behavior/Behavior.More/Delegators/Delegator.SubmitLink.js
mootools_behavior/static/mootools_behavior/Behavior.More/Drag/Behavior.Resizable.js
mootools_behavior/static/mootools_behavior/Behavior.More/Drag/Behavior.Sortable.js
mootools_behavior/static/mootools_behavior/Behavior.More/Forms/Behavior.FormRequest.js
mootools_behavior/static/mootools_behavior/Behavior.More/Forms/Behavior.FormValidator.js
mootools_behavior/static/mootools_behavior/Behavior.More/Forms/Behavior.OverText.js
mootools_behavior/static/mootools_behavior/Behavior.More/Fx/Behavior.FxAccordion.js
mootools_behavior/static/mootools_behavior/Behavior.More/Interface/Behavior.HtmlTable.js
mootools_behavior/templatetags/__init__.py
mootools_behavior/templatetags/mootools_behavior.py