Metadata-Version: 1.1
Name: django-mootools-behavior
Version: 0.1.1
Summary: Utilities for https://github.com/anutron/behavior integration with django.
Home-page: http://bitbucket.org/kmike/django-mootools-behavior/
Author: Mikhail Korobov
Author-email: kmike84@gmail.com
License: MIT license
Download-URL: http://bitbucket.org/kmike/django-mootools-behavior/get/tip.zip
Platform: UNKNOWN
Classifier: Development Status :: 4 - Beta
Classifier: Framework :: Django
Classifier: Intended Audience :: Developers
Classifier: License :: OSI Approved :: MIT License
Classifier: Programming Language :: Python
Classifier: Topic :: Software Development :: Libraries :: Python Modules
Requires: django
